roentgen/__init__.py
roentgen/config.json
roentgen/icon.py
roentgen/icon_collection.py
roentgen/shapes.json
roentgen_icons-0.12.0.dist-info/METADATA
roentgen_icons-0.12.0.dist-info/WHEEL
roentgen_icons-0.12.0.dist-info/licenses/LICENSE
roentgen_icons-0.12.0.dist-info/RECORD
