Metadata-Version: 2.4
Name: roentgen-icons
Version: 0.12.0
Summary: Set of monochrome 14 × 14 px pixel-aligned map icons
Project-URL: Homepage, https://enzet.ru/roentgen
Project-URL: Repository, https://github.com/enzet/Roentgen
Author-email: Sergey Vartanov <me@enzet.ru>
License-File: LICENSE
Classifier: Operating System :: OS Independent
Classifier: Programming Language :: Python :: 3
Classifier: Topic :: Multimedia :: Graphics
Requires-Python: >=3.10
Requires-Dist: colour~=0.1.5
Requires-Dist: lxml~=5.4.0
Requires-Dist: requests~=2.32.3
Requires-Dist: svgpathtools~=1.6.1
Requires-Dist: svgwrite~=1.4.3
Provides-Extra: dev
Requires-Dist: build~=1.0.0; extra == 'dev'
Requires-Dist: pytest~=8.0.0; extra == 'dev'
Requires-Dist: ruff~=0.11.12; extra == 'dev'
